{
"type": "FeatureCollection",
"name": "BCNSPP",
"crs": { "type": "name", "properties": { "name": "urn:ogc:def:crs:OGC:1.3:CRS84" } },
"features": [
{ "type": "Feature", "properties": { "RCID": 1, "PRIM": 1, "GRUP": 2, "OBJL": 9, "RVER": 1, "AGEN": 550, "FIDN": 255881351, "FIDS": 3589, "LNAM": "02260F4070870E05", "LNAM_REFS": [ "02260F4058B10E05", "02260F4065E80E05" ], "FFPT_RIND": [ 2, 2 ], "BCNSHP": 5, "CATSPM": [ "16" ], "COLOUR": [ ], "OBJNAM": "Government Island Lower Range Front Light", "STATUS": [ "1" ], "SCAMIN": 59999, "SORDAT": "20121030", "SORIND": "US,US,reprt,13thCGD,LNM 44/12" }, "geometry": { "type": "Point", "coordinates": [ -122.4988558, 45.5807122 ] } },
{ "type": "Feature", "properties": { "RCID": 2, "PRIM": 1, "GRUP": 2, "OBJL": 9, "RVER": 1, "AGEN": 550, "FIDN": 255881355, "FIDS": 3589, "LNAM": "02260F40708B0E05", "LNAM_REFS": [ "02260F4058B30E05", "02260F4065EA0E05" ], "FFPT_RIND": [ 2, 2 ], "BCNSHP": 4, "CATSPM": [ "16" ], "COLOUR": [ ], "OBJNAM": "Government Island Lower Range Rear Light", "STATUS": [ "1" ], "SCAMIN": 59999, "SORDAT": "20121030", "SORIND": "US,US,reprt,13thCGD,LNM 44/12" }, "geometry": { "type": "Point", "coordinates": [ -122.4945933, 45.5793342 ] } },
{ "type": "Feature", "properties": { "RCID": 3, "PRIM": 1, "GRUP": 2, "OBJL": 9, "RVER": 1, "AGEN": 550, "FIDN": 255881341, "FIDS": 3589, "LNAM": "02260F40707D0E05", "LNAM_REFS": [ "02260F4058AE0E05", "02260F4065E50E05" ], "FFPT_RIND": [ 2, 2 ], "BCNSHP": 5, "CATSPM": [ "16" ], "COLOUR": [ ], "OBJNAM": "Government Island Middle Range Rear Light", "STATUS": [ "1" ], "SCAMIN": 59999, "SORDAT": "20121030", "SORIND": "US,US,reprt,13thCGD,LNM 44/12" }, "geometry": { "type": "Point", "coordinates": [ -122.5347842, 45.5876092 ] } },
{ "type": "Feature", "properties": { "RCID": 4, "PRIM": 1, "GRUP": 2, "OBJL": 9, "RVER": 1, "AGEN": 550, "FIDN": 255881346, "FIDS": 3589, "LNAM": "02260F4070820E05", "LNAM_REFS": [ "02260F4058B00E05", "02260F223B700E10", "02260F4065E60E05" ], "FFPT_RIND": [ 2, 2, 2 ], "BCNSHP": 5, "CATSPM": [ "16" ], "COLOUR": [ ], "OBJNAM": "Government Island Middle Range Front Light", "STATUS": [ "1" ], "SCAMIN": 59999, "SORDAT": "20121030", "SORIND": "US,US,reprt,13thCGD,LNM 44/12" }, "geometry": { "type": "Point", "coordinates": [ -122.5319122, 45.5873294 ] } }
]
}
