{
"type": "FeatureCollection",
"name": "DAYMAR",
"crs": { "type": "name", "properties": { "name": "urn:ogc:def:crs:OGC:1.3:CRS84" } },
"features": [
{ "type": "Feature", "properties": { "RCID": 13, "PRIM": 1, "GRUP": 2, "OBJL": 39, "RVER": 1, "AGEN": 550, "FIDN": 255875287, "FIDS": 3589, "LNAM": "02260F4058D70E05", "COLOUR": [ "3", "3" ], "COLPAT": [ "6" ], "TOPSHP": 24, "SCAMIN": 59999, "SORDAT": "20041129", "SORIND": "US,US,reprt,13thCGD,ATONIS" }, "geometry": { "type": "Point", "coordinates": [ -122.3555511, 45.5686064 ] } },
{ "type": "Feature", "properties": { "RCID": 14, "PRIM": 1, "GRUP": 2, "OBJL": 39, "RVER": 1, "AGEN": 550, "FIDN": 255875282, "FIDS": 3589, "LNAM": "02260F4058D20E05", "COLOUR": [ "6", "6" ], "COLPAT": [ "6" ], "TOPSHP": 12, "SCAMIN": 59999, "SORDAT": "20230208", "SORIND": "US,US,reprt,13thCGD,LNM 06/23" }, "geometry": { "type": "Point", "coordinates": [ -122.3430919, 45.5522528 ] } },
{ "type": "Feature", "properties": { "RCID": 15, "PRIM": 1, "GRUP": 2, "OBJL": 39, "RVER": 1, "AGEN": 550, "FIDN": 255875283, "FIDS": 3589, "LNAM": "02260F4058D30E05", "COLOUR": [ "6", "6" ], "COLPAT": [ "6" ], "TOPSHP": 12, "SCAMIN": 59999, "SORDAT": "20230208", "SORIND": "US,US,reprt,13thCGD,LNM 06/23" }, "geometry": { "type": "Point", "coordinates": [ -122.3398297, 45.551805 ] } },
{ "type": "Feature", "properties": { "RCID": 16, "PRIM": 1, "GRUP": 2, "OBJL": 39, "RVER": 1, "AGEN": 550, "FIDN": 255875290, "FIDS": 3589, "LNAM": "02260F4058DA0E05", "COLOUR": [ "3", "2", "3" ], "COLPAT": [ "2" ], "TOPSHP": 21, "SCAMIN": 59999, "SORDAT": "20130319", "SORIND": "US,US,reprt,13thCGD,LNM 12/13" }, "geometry": { "type": "Point", "coordinates": [ -122.3436458, 45.5673331 ] } },
{ "type": "Feature", "properties": { "RCID": 17, "PRIM": 1, "GRUP": 2, "OBJL": 39, "RVER": 1, "AGEN": 550, "FIDN": 309870148, "FIDS": 2009, "LNAM": "022612783E4407D9", "CATSPM": [ "27" ], "COLOUR": [ "11", "1" ], "COLPAT": [ "6" ], "TOPSHP": 12, "SCAMIN": 59999, "SORDAT": "20221005", "SORIND": "US,US,reprt,13thCGD,LNM 40/22" }, "geometry": { "type": "Point", "coordinates": [ -122.343975, 45.5559781 ] } },
{ "type": "Feature", "properties": { "RCID": 18, "PRIM": 1, "GRUP": 2, "OBJL": 39, "RVER": 1, "AGEN": 550, "FIDN": 255875291, "FIDS": 3589, "LNAM": "02260F4058DB0E05", "COLOUR": [ "3", "2", "3" ], "COLPAT": [ "2" ], "TOPSHP": 21, "SCAMIN": 59999, "SORDAT": "20130319", "SORIND": "US,US,reprt,13thCGD,LNM 12/13" }, "geometry": { "type": "Point", "coordinates": [ -122.3388464, 45.5662131 ] } },
{ "type": "Feature", "properties": { "RCID": 19, "PRIM": 1, "GRUP": 2, "OBJL": 39, "RVER": 1, "AGEN": 550, "FIDN": 188815725, "FIDS": 5460, "LNAM": "02260B41196D1554", "COLOUR": [ "6", "6" ], "COLPAT": [ "6" ], "TOPSHP": 12, "SCAMIN": 59999, "SORDAT": "20230419", "SORIND": "US,US,reprt,13thCGD,LNM 16/23" }, "geometry": { "type": "Point", "coordinates": [ -122.3378653, 45.5489208 ] } },
{ "type": "Feature", "properties": { "RCID": 20, "PRIM": 1, "GRUP": 2, "OBJL": 39, "RVER": 1, "AGEN": 550, "FIDN": 255875288, "FIDS": 3589, "LNAM": "02260F4058D80E05", "COLOUR": [ "3", "3" ], "COLPAT": [ "6" ], "TOPSHP": 24, "SCAMIN": 59999, "SORDAT": "20041220", "SORIND": "US,US,reprt,13thCGD,ATONIS" }, "geometry": { "type": "Point", "coordinates": [ -122.3473142, 45.5601514 ] } }
]
}
