{
"type": "FeatureCollection",
"name": "LIGHTS",
"crs": { "type": "name", "properties": { "name": "urn:ogc:def:crs:OGC:1.3:CRS84" } },
"features": [
{ "type": "Feature", "properties": { "RCID": 21, "PRIM": 1, "GRUP": 2, "OBJL": 75, "RVER": 1, "AGEN": 550, "FIDN": 255878677, "FIDS": 3589, "LNAM": "02260F4066150E05", "CATLIT": [ ], "COLOUR": [ "3" ], "EXCLIT": 4, "HEIGHT": 10.9, "LITCHR": 2, "SIGGRP": "(1)", "SIGPER": 2.5, "SIGSEQ": "00.3+(02.2)", "VALNMR": 4.0, "SCAMIN": 59999, "SORDAT": "20201124", "SORIND": "US,US,reprt,13thCGD,LNM 47/20" }, "geometry": { "type": "Point", "coordinates": [ -122.3555511, 45.5686064 ] } },
{ "type": "Feature", "properties": { "RCID": 22, "PRIM": 1, "GRUP": 2, "OBJL": 75, "RVER": 1, "AGEN": 550, "FIDN": 255878680, "FIDS": 3589, "LNAM": "02260F4066180E05", "CATLIT": [ "4", "12" ], "COLOUR": [ "4" ], "EXCLIT": 4, "HEIGHT": 13.4, "LITCHR": 2, "SIGGRP": "(1)", "SIGPER": 2.5, "SIGSEQ": "00.3+(02.2)", "SCAMIN": 59999, "SORDAT": "20130319", "SORIND": "US,US,reprt,13thCGD,LNM 12/13" }, "geometry": { "type": "Point", "coordinates": [ -122.3436458, 45.5673331 ] } },
{ "type": "Feature", "properties": { "RCID": 23, "PRIM": 1, "GRUP": 2, "OBJL": 75, "RVER": 1, "AGEN": 550, "FIDN": 468468468, "FIDS": 2009, "LNAM": "02261BEC42F407D9", "CATLIT": [ ], "COLOUR": [ "3" ], "EXCLIT": 4, "LITCHR": 2, "SIGGRP": "(1)", "SIGPER": 2.5, "SIGSEQ": "00.3+(02.2)", "VALNMR": 4.0, "SCAMIN": 59999, "SORDAT": "20221005", "SORIND": "US,US,reprt,13thCGD,LNM 40/22" }, "geometry": { "type": "Point", "coordinates": [ -122.3378439, 45.5552778 ] } },
{ "type": "Feature", "properties": { "RCID": 24, "PRIM": 1, "GRUP": 2, "OBJL": 75, "RVER": 1, "AGEN": 550, "FIDN": 255878671, "FIDS": 3589, "LNAM": "02260F40660F0E05", "CATLIT": [ ], "COLOUR": [ "6" ], "EXCLIT": 4, "HEIGHT": 7.6, "LITCHR": 2, "SIGGRP": "(1)", "SIGPER": 6.0, "SIGSEQ": "00.6+(05.4)", "VALNMR": 4.0, "SCAMIN": 59999, "SORDAT": "20230208", "SORIND": "US,US,reprt,13thCGD,LNM 06/23" }, "geometry": { "type": "Point", "coordinates": [ -122.3430919, 45.5522528 ] } },
{ "type": "Feature", "properties": { "RCID": 25, "PRIM": 1, "GRUP": 2, "OBJL": 75, "RVER": 1, "AGEN": 550, "FIDN": 255878673, "FIDS": 3589, "LNAM": "02260F4066110E05", "CATLIT": [ ], "COLOUR": [ "6" ], "EXCLIT": 4, "HEIGHT": 11.8, "LITCHR": 2, "SIGGRP": "(1)", "SIGPER": 2.5, "SIGSEQ": "00.3+(02.2)", "VALNMR": 4.0, "SCAMIN": 59999, "SORDAT": "20230208", "SORIND": "US,US,reprt,13thCGD,LNM 06/23" }, "geometry": { "type": "Point", "coordinates": [ -122.3398297, 45.551805 ] } },
{ "type": "Feature", "properties": { "RCID": 26, "PRIM": 1, "GRUP": 2, "OBJL": 75, "RVER": 1, "AGEN": 550, "FIDN": 255878682, "FIDS": 3589, "LNAM": "02260F40661A0E05", "CATLIT": [ "4", "13" ], "COLOUR": [ "4" ], "EXCLIT": 4, "HEIGHT": 18.8, "LITCHR": 7, "SECTR1": 102.6, "SECTR2": 113.6, "SIGGRP": "(1)", "SIGPER": 6.0, "SIGSEQ": "03.0+(03.0)", "SCAMIN": 59999, "SORDAT": "20130319", "SORIND": "US,US,reprt,13thCGD,LNM 12/13" }, "geometry": { "type": "Point", "coordinates": [ -122.3388464, 45.5662131 ] } },
{ "type": "Feature", "properties": { "RCID": 27, "PRIM": 1, "GRUP": 2, "OBJL": 75, "RVER": 1, "AGEN": 550, "FIDN": 805129463, "FIDS": 5460, "LNAM": "02262FFD4CF71554", "CATLIT": [ ], "COLOUR": [ "6" ], "EXCLIT": 4, "HEIGHT": 30.0, "LITCHR": 2, "SIGGRP": "(1)", "SIGPER": 4.0, "SIGSEQ": "00.4+(03.6)", "VALNMR": 4.0, "SCAMIN": 59999, "SORDAT": "20230419", "SORIND": "US,US,reprt,13thCGD,LNM 16/23" }, "geometry": { "type": "Point", "coordinates": [ -122.3378653, 45.5489208 ] } },
{ "type": "Feature", "properties": { "RCID": 28, "PRIM": 1, "GRUP": 2, "OBJL": 75, "RVER": 1, "AGEN": 550, "FIDN": 255878662, "FIDS": 3589, "LNAM": "02260F4066060E05", "CATLIT": [ "5" ], "COLOUR": [ "1", "4" ], "EXCLIT": 4, "LITCHR": 19, "LITVIS": [ "1" ], "SIGGRP": "()", "SCAMIN": 59999, "SORDAT": "20011110", "SORIND": "US,US,graph,Chart 18531" }, "geometry": { "type": "Point", "coordinates": [ -122.3989183, 45.5510205 ] } },
{ "type": "Feature", "properties": { "RCID": 29, "PRIM": 1, "GRUP": 2, "OBJL": 75, "RVER": 1, "AGEN": 550, "FIDN": 255878679, "FIDS": 3589, "LNAM": "02260F4066170E05", "CATLIT": [ ], "COLOUR": [ "3" ], "EXCLIT": 4, "HEIGHT": 4.8, "LITCHR": 2, "SIGGRP": "(1)", "SIGPER": 4.0, "SIGSEQ": "00.4+(03.6)", "VALNMR": 4.0, "SCAMIN": 59999, "SORDAT": "20210407", "SORIND": "US,US,reprt,13thCGD,LNM 14/21" }, "geometry": { "type": "Point", "coordinates": [ -122.3473142, 45.5601514 ] } }
]
}
