{
"type": "FeatureCollection",
"name": "BOYLAT",
"crs": { "type": "name", "properties": { "name": "urn:ogc:def:crs:OGC:1.3:CRS84" } },
"features": [
{ "type": "Feature", "properties": { "RCID": 6, "PRIM": 1, "GRUP": 2, "OBJL": 17, "RVER": 1, "AGEN": 550, "FIDN": 255874683, "FIDS": 3589, "LNAM": "02260F40567B0E05", "BOYSHP": 1, "CATLAM": 2, "COLOUR": [ "3" ], "OBJNAM": "Cape Horn Buoy 68", "STATUS": [ "1" ], "SCAMIN": 59999, "SORDAT": "20100907", "SORIND": "US,US,reprt,13thCGD,LNM 36/10" }, "geometry": { "type": "Point", "coordinates": [ -122.1982353, 45.5652436 ] } },
{ "type": "Feature", "properties": { "RCID": 7, "PRIM": 1, "GRUP": 2, "OBJL": 17, "RVER": 1, "AGEN": 550, "FIDN": 331495987, "FIDS": 12345, "LNAM": "022613C23A333039", "LNAM_REFS": [ "022608BDE0653039" ], "FFPT_RIND": [ 2 ], "BOYSHP": 4, "CATLAM": 2, "COLOUR": [ "3" ], "OBJNAM": "Candiana Lighted Buoy 70", "STATUS": [ "1" ], "SCAMIN": 59999, "SORDAT": "20150407", "SORIND": "US,US,reprt,13thCGD,LNM 14/15" }, "geometry": { "type": "Point", "coordinates": [ -122.1877069, 45.5717433 ] } }
]
}
